{
  "projects": [
    {
      "id": 1,
      "title": "Criar banner da pagina principal (Editado)",
      "details": "Lorem ipsum dolor sit amet consectetur adipisicing elit.",
      "complete": true
    },
    {
      "id": 2,
      "title": "Enviar e-mail de marketing",
      "details": "Lorem ipsum dolor sit amet consectetur adipisicing elit. Illum beatae iure eligendi voluptatem.",
      "complete": true
    },
    {
      "title": "Projeto Teste",
      "details": "Detalhes de projeto",
      "complete": false,
      "id": 3
    },
    {
      "title": "1234",
      "details": "1234",
      "complete": false,
      "id": 4
    }
  ],
  "tasks": [
    {
      "projectId": "1",
      "task": "Adaptar tela",
      "done": false,
      "id": 1
    },
    {
      "projectId": "1",
      "task": "Adaptar botões",
      "done": false,
      "id": 2
    },
    [
      {
        "task": "1234",
        "projectId": 4,
        "done": false
      }
    ],
    [
      {
        "task": "1234",
        "projectId": 4,
        "done": false
      }
    ],
    [
      {
        "task": "1234",
        "projectId": 4,
        "done": false
      }
    ],
    [
      {
        "task": "1234",
        "projectId": 4,
        "done": false
      }
    ],
    [
      {
        "task": ""
      }
    ],
    [
      {
        "task": ""
      }
    ],
    [
      {
        "task": "abcd",
        "projectId": 4,
        "done": false
      }
    ]
  ]
}